revaisor_genaitesting/__init__.py
revaisor_genaitesting/client.py
revaisor_genaitesting/api_requests/__init__.py
revaisor_genaitesting/api_requests/api_requests.py
revaisor_genaitesting/utils/__init__.py
revaisor_genaitesting/utils/camelCase.py
revaisor_genaitesting/utils/summary.py
revaisor_genaitesting-0.0.1.dist-info/METADATA
revaisor_genaitesting-0.0.1.dist-info/WHEEL
revaisor_genaitesting-0.0.1.dist-info/top_level.txt
revaisor_genaitesting-0.0.1.dist-info/RECORD
